dictoria/__init__.py
dictoria/dictoria.py
dictoria-0.1.9.dist-info/LICENSE
dictoria-0.1.9.dist-info/METADATA
dictoria-0.1.9.dist-info/WHEEL
dictoria-0.1.9.dist-info/RECORD
