Metadata-Version: 2.3
Name: dictoria
Version: 0.1.9
Summary: A dictionary extension that supports regex-based key search.
License: MIT
Author: tamerlan
Author-email: tamerlanlarsanov@gmail.com
Requires-Python: >=3.12
Classifier: License :: OSI Approved :: MIT License
Classifier: Programming Language :: Python :: 3
Classifier: Programming Language :: Python :: 3.12
Classifier: Programming Language :: Python :: 3.13
